xicam/threadmonitor/__init__.py
xicam/threadmonitor/threadmonitor.yapsy-plugin
xicam.threadmonitor-0.1.0.dist-info/DESCRIPTION.rst
xicam.threadmonitor-0.1.0.dist-info/METADATA
xicam.threadmonitor-0.1.0.dist-info/RECORD
xicam.threadmonitor-0.1.0.dist-info/WHEEL
xicam.threadmonitor-0.1.0.dist-info/metadata.json
xicam.threadmonitor-0.1.0.dist-info/top_level.txt
